[
  {
    "author": "magnim",
    "link_thumb": "https://live.staticflickr.com/65535/51786523962_73c12bbf95_o.gif",
    "link_bin": "https://github.com/lmbstudiocontact/mb6_0/raw/main/466.bin",
    "id_bin": "466",
    "list_language": [],
    "array_tags": [
      "digital",
      "miband6",
      "distance",
      "pulse",
      "weather",
      "pai",
      "calories",
      "steps"
    ],
    "list_album": [
      {
        "id_album": "2433880",
        "link_thumb": "https://live.staticflickr.com/65535/51786523962_73c12bbf95_o.gif",
        "title": "None"
      }
    ]
  },
  {
    "author": "CTEPE0",
    "link_thumb": "https://live.staticflickr.com/65535/51787960104_cedde1dca0_o.gif",
    "link_bin": "https://github.com/lmbstudiocontact/mb6_0/raw/main/581.bin",
    "id_bin": "581",
    "list_language": [],
    "array_tags": [
      "animation"
    ],
    "list_album": [
      {
        "id_album": "-2075887794",
        "link_thumb": "https://live.staticflickr.com/65535/51787960104_cedde1dca0_o.gif",
        "title": "Cartoon"
      }
    ]
  },
  {
    "author": "brunello",
    "link_thumb": "https://live.staticflickr.com/65535/51787975594_d3a05fcbe5_o.gif",
    "link_bin": "https://github.com/lmbstudiocontact/mb6_0/raw/main/241.bin",
    "id_bin": "241",
    "list_language": [],
    "array_tags": [
      "seconds",
      "heartrate",
      "steps"
    ],
    "list_album": [
      {
        "id_album": "2433880",
        "link_thumb": "https://live.staticflickr.com/65535/51787975594_d3a05fcbe5_o.gif",
        "title": "None"
      }
    ]
  },
  {
    "author": "TsReal30",
    "link_thumb": "https://live.staticflickr.com/65535/51788218015_015c9c6cc6_o.gif",
    "link_bin": "https://github.com/lmbstudiocontact/mb6_0/raw/main/1110.bin",
    "id_bin": "1110",
    "list_language": [],
    "array_tags": [],
    "list_album": [
      {
        "id_album": "2211858",
        "link_thumb": "https://live.staticflickr.com/65535/51788218015_015c9c6cc6_o.gif",
        "title": "Game"
      }
    ]
  },
  {
    "author": "KrakeCZ",
    "link_thumb": "https://live.staticflickr.com/65535/51787593718_4204549b38_o.gif",
    "link_bin": "https://github.com/lmbstudiocontact/mb6_0/raw/main/1136.bin",
    "id_bin": "1136",
    "list_language": [],
    "array_tags": [
      "digital",
      "date",
      "distance",
      "heartrate",
      "weather",
      "calories",
      "battery",
      "steps"
    ],
    "list_album": [
      {
        "id_album": "2433880",
        "link_thumb": "https://live.staticflickr.com/65535/51787593718_4204549b38_o.gif",
        "title": "None"
      }
    ]
  },
  {
    "author": "Dijkmeneer",
    "link_thumb": "https://live.staticflickr.com/65535/51787592448_8690c0bfc9_o.gif",
    "link_bin": "https://github.com/lmbstudiocontact/mb6_0/raw/main/1171.bin",
    "id_bin": "1171",
    "list_language": [],
    "array_tags": [
      "kcal",
      "stepprogress",
      "distance",
      "heartrate",
      "pai",
      "time",
      "steps"
    ],
    "list_album": [
      {
        "id_album": "2433880",
        "link_thumb": "https://live.staticflickr.com/65535/51787592448_8690c0bfc9_o.gif",
        "title": "None"
      }
    ]
  },
  {
    "author": "JM7087",
    "link_thumb": "https://live.staticflickr.com/65535/51788226655_a40474d4a1_o.gif",
    "link_bin": "https://github.com/lmbstudiocontact/mb6_0/raw/main/34.bin",
    "id_bin": "34",
    "list_language": [],
    "array_tags": [
      "digital",
      "date",
      "distance",
      "calories",
      "battery",
      "steps"
    ],
    "list_album": [
      {
        "id_album": "2211858",
        "link_thumb": "https://live.staticflickr.com/65535/51788226655_a40474d4a1_o.gif",
        "title": "Game"
      }
    ]
  },
  {
    "author": "Phobos666",
    "link_thumb": "https://live.staticflickr.com/65535/51787342186_ce88e41020_o.gif",
    "link_bin": "https://github.com/lmbstudiocontact/mb6_0/raw/main/453.bin",
    "id_bin": "453",
    "list_language": [],
    "array_tags": [
      "pai"
    ],
    "list_album": [
      {
        "id_album": "2433880",
        "link_thumb": "https://live.staticflickr.com/65535/51787342186_ce88e41020_o.gif",
        "title": "None"
      }
    ]
  },
  {
    "author": "MAXSTILL",
    "link_thumb": "https://live.staticflickr.com/65535/51787971339_85aba3d336_o.gif",
    "link_bin": "https://github.com/lmbstudiocontact/mb6_0/raw/main/332.bin",
    "id_bin": "332",
    "list_language": [],
    "array_tags": [
      "date",
      "games",
      "battery"
    ],
    "list_album": [
      {
        "id_album": "2211858",
        "link_thumb": "https://live.staticflickr.com/65535/51787971339_85aba3d336_o.gif",
        "title": "Game"
      }
    ]
  },
  {
    "author": "zyfish",
    "link_thumb": "https://live.staticflickr.com/65535/51786536667_f2fa455560_o.gif",
    "link_bin": "https://github.com/lmbstudiocontact/mb6_0/raw/main/5.bin",
    "id_bin": "5",
    "list_language": [],
    "array_tags": [
      "digital",
      "date",
      "heartrate",
      "weather",
      "battery",
      "steps"
    ],
    "list_album": [
      {
        "id_album": "2433880",
        "link_thumb": "https://live.staticflickr.com/65535/51786536667_f2fa455560_o.gif",
        "title": "None"
      }
    ]
  },
  {
    "author": "KrakeCZ",
    "link_thumb": "https://live.staticflickr.com/65535/51786529497_7747beb242_o.gif",
    "link_bin": "https://github.com/lmbstudiocontact/mb6_0/raw/main/1047.bin",
    "id_bin": "1047",
    "list_language": [],
    "array_tags": [
      "digital",
      "date",
      "distance",
      "heartrate",
      "weather",
      "battery",
      "steps"
    ],
    "list_album": [
      {
        "id_album": "2433880",
        "link_thumb": "https://live.staticflickr.com/65535/51786529497_7747beb242_o.gif",
        "title": "None"
      }
    ]
  },
  {
    "author": "raxdata",
    "link_thumb": "https://live.staticflickr.com/65535/51787966994_9d92ce28b8_o.gif",
    "link_bin": "https://github.com/lmbstudiocontact/mb6_0/raw/main/1189.bin",
    "id_bin": "1189",
    "list_language": [],
    "array_tags": [
      "digital",
      "date",
      "distance",
      "heartrate",
      "weather",
      "calories",
      "battery",
      "steps"
    ],
    "list_album": [
      {
        "id_album": "2433880",
        "link_thumb": "https://live.staticflickr.com/65535/51787966994_9d92ce28b8_o.gif",
        "title": "None"
      }
    ]
  }
]