[
  {
    "author": "ZanarkTempest",
    "link_thumb": "https://live.staticflickr.com/65535/51670265569_b4ea47efe3_o.gif",
    "link_bin": "https://github.com/lmbstudiocontact/mb6_1/raw/main/1901.bin",
    "id_bin": "1901",
    "list_language": [],
    "array_tags": [
      "cartoon"
    ],
    "list_album": [
      {
        "id_album": "-2075887794",
        "link_thumb": "https://live.staticflickr.com/65535/51670265569_b4ea47efe3_o.gif",
        "title": "Cartoon"
      }
    ]
  },
  {
    "author": "shymik",
    "link_thumb": "https://live.staticflickr.com/65535/51669470826_9557971b65_o.gif",
    "link_bin": "https://github.com/lmbstudiocontact/mb6_0/raw/main/1097.bin",
    "id_bin": "1097",
    "list_language": [],
    "array_tags": [
      "digital",
      "date",
      "floors",
      "distance",
      "heartrate",
      "weather",
      "calories",
      "battery",
      "steps"
    ],
    "list_album": [
      {
        "id_album": "2433880",
        "link_thumb": "https://live.staticflickr.com/65535/51669470826_9557971b65_o.gif",
        "title": "None"
      }
    ]
  },
  {
    "author": "magnim",
    "link_thumb": "https://live.staticflickr.com/65535/51668948567_f0a37030e6_o.gif",
    "link_bin": "https://github.com/lmbstudiocontact/mb6_0/raw/main/618.bin",
    "id_bin": "618",
    "list_language": [],
    "array_tags": [
      "digital",
      "weather",
      "pulse",
      "calories",
      "steps",
      "colors"
    ],
    "list_album": [
      {
        "id_album": "2433880",
        "link_thumb": "https://live.staticflickr.com/65535/51668948567_f0a37030e6_o.gif",
        "title": "None"
      }
    ]
  },
  {
    "author": "uplush",
    "link_thumb": "https://live.staticflickr.com/65535/51670510634_dd9ea2274b_o.gif",
    "link_bin": "https://github.com/lmbstudiocontact/mb6_1/raw/main/991.bin",
    "id_bin": "991",
    "list_language": [],
    "array_tags": [
      "pokemon",
      "games"
    ],
    "list_album": [
      {
        "id_album": "63410260",
        "link_thumb": "https://live.staticflickr.com/65535/51670510634_dd9ea2274b_o.gif",
        "title": "Anime"
      }
    ]
  },
  {
    "author": "mpsspencer",
    "link_thumb": "https://live.staticflickr.com/65535/51670048308_4f49b932a6_o.gif",
    "link_bin": "https://github.com/lmbstudiocontact/mb6_0/raw/main/914.bin",
    "id_bin": "914",
    "list_language": [],
    "array_tags": [
      "date",
      "bluetooth",
      "notdisturb",
      "lock",
      "time",
      "battery"
    ],
    "list_album": [
      {
        "id_album": "2433880",
        "link_thumb": "https://live.staticflickr.com/65535/51670048308_4f49b932a6_o.gif",
        "title": "None"
      }
    ]
  },
  {
    "author": "brunello",
    "link_thumb": "https://live.staticflickr.com/65535/51669900508_06ab64da23_o.gif",
    "link_bin": "https://github.com/lmbstudiocontact/mb6_0/raw/main/241.bin",
    "id_bin": "241",
    "list_language": [],
    "array_tags": [
      "seconds",
      "heartrate",
      "steps"
    ],
    "list_album": [
      {
        "id_album": "2433880",
        "link_thumb": "https://live.staticflickr.com/65535/51669900508_06ab64da23_o.gif",
        "title": "None"
      }
    ]
  },
  {
    "author": "TsReal30",
    "link_thumb": "https://live.staticflickr.com/65535/51669513966_f0ab734013_o.gif",
    "link_bin": "https://github.com/lmbstudiocontact/mb6_0/raw/main/146.bin",
    "id_bin": "146",
    "list_language": [],
    "array_tags": [
      "naruto"
    ],
    "list_album": [
      {
        "id_album": "63410260",
        "link_thumb": "https://live.staticflickr.com/65535/51669513966_f0ab734013_o.gif",
        "title": "Anime"
      }
    ]
  },
  {
    "author": "Вепрь",
    "link_thumb": "https://live.staticflickr.com/65535/51668733647_5fd15e1315_o.gif",
    "link_bin": "https://github.com/lmbstudiocontact/mb6_0/raw/main/1625.bin",
    "id_bin": "1625",
    "list_language": [],
    "array_tags": [
      "digital",
      "date",
      "distance",
      "heartrate",
      "weather",
      "battery",
      "steps"
    ],
    "list_album": [
      {
        "id_album": "2433880",
        "link_thumb": "https://live.staticflickr.com/65535/51668733647_5fd15e1315_o.gif",
        "title": "None"
      }
    ]
  },
  {
    "author": "yaoun",
    "link_thumb": "https://live.staticflickr.com/65535/51670550915_c1c65b5b0c_o.gif",
    "link_bin": "https://github.com/lmbstudiocontact/mb6_0/raw/main/287.bin",
    "id_bin": "287",
    "list_language": [],
    "array_tags": [
      "digital",
      "date",
      "distance",
      "heartrate",
      "calories",
      "battery",
      "steps",
      "sun",
      "seconds",
      "floors",
      "weather",
      "alarm"
    ],
    "list_album": [
      {
        "id_album": "2433880",
        "link_thumb": "https://live.staticflickr.com/65535/51670550915_c1c65b5b0c_o.gif",
        "title": "None"
      }
    ]
  },
  {
    "author": "CTEPE0",
    "link_thumb": "https://live.staticflickr.com/65535/51669763621_8fdbb5f12d_o.gif",
    "link_bin": "https://github.com/lmbstudiocontact/mb6_0/raw/main/701.bin",
    "id_bin": "701",
    "list_language": [],
    "array_tags": [
      "cosmic"
    ],
    "list_album": [
      {
        "id_album": "2433880",
        "link_thumb": "https://live.staticflickr.com/65535/51669763621_8fdbb5f12d_o.gif",
        "title": "None"
      }
    ]
  },
  {
    "author": "Dijkmeneer",
    "link_thumb": "https://live.staticflickr.com/65535/51669479766_6718ce8bdb_o.gif",
    "link_bin": "https://github.com/lmbstudiocontact/mb6_0/raw/main/1171.bin",
    "id_bin": "1171",
    "list_language": [],
    "array_tags": [
      "kcal",
      "distance",
      "heartrate",
      "pai",
      "time",
      "steps"
    ],
    "list_album": [
      {
        "id_album": "2433880",
        "link_thumb": "https://live.staticflickr.com/65535/51669479766_6718ce8bdb_o.gif",
        "title": "None"
      }
    ]
  },
  {
    "author": "magnim",
    "link_thumb": "https://live.staticflickr.com/65535/51670401624_b868af199e_o.gif",
    "link_bin": "https://github.com/lmbstudiocontact/mb6_0/raw/main/466.bin",
    "id_bin": "466",
    "list_language": [],
    "array_tags": [
      "digital",
      "distance",
      "pulse",
      "weather",
      "pai",
      "calories",
      "steps"
    ],
    "list_album": [
      {
        "id_album": "2433880",
        "link_thumb": "https://live.staticflickr.com/65535/51670401624_b868af199e_o.gif",
        "title": "None"
      }
    ]
  }
]