[
  {
    "author": "KrakeCZ",
    "link_thumb": "https://live.staticflickr.com/65535/51669717203_0c76383949_o.gif",
    "link_bin": "https://github.com/lmbstudiocontact/mb6_0/raw/main/1136.bin",
    "id_bin": "1136",
    "list_language": [],
    "array_tags": [
      "digital",
      "date",
      "distance",
      "heartrate",
      "weather",
      "calories",
      "battery",
      "steps"
    ],
    "list_album": [
      {
        "id_album": "2433880",
        "link_thumb": "https://live.staticflickr.com/65535/51669717203_0c76383949_o.gif",
        "title": "None"
      }
    ]
  },
  {
    "author": "zantfaul",
    "link_thumb": "https://live.staticflickr.com/65535/51668952692_c5185dc1f5_o.gif",
    "link_bin": "https://github.com/lmbstudiocontact/mb6_0/raw/main/642.bin",
    "id_bin": "642",
    "list_language": [],
    "array_tags": [
      "digital",
      "month",
      "english",
      "battery",
      "day",
      "anime"
    ],
    "list_album": [
      {
        "id_album": "63410260",
        "link_thumb": "https://live.staticflickr.com/65535/51668952692_c5185dc1f5_o.gif",
        "title": "Anime"
      }
    ]
  },
  {
    "author": "KrakeCZ",
    "link_thumb": "https://live.staticflickr.com/65535/51669704458_3246afa4cc_o.gif",
    "link_bin": "https://github.com/lmbstudiocontact/mb6_0/raw/main/1030.bin",
    "id_bin": "1030",
    "list_language": [],
    "array_tags": [
      "digital",
      "date",
      "distance",
      "heartrate",
      "weather",
      "calories",
      "battery",
      "steps"
    ],
    "list_album": [
      {
        "id_album": "2433880",
        "link_thumb": "https://live.staticflickr.com/65535/51669704458_3246afa4cc_o.gif",
        "title": "None"
      }
    ]
  },
  {
    "author": "Rosta949",
    "link_thumb": "https://live.staticflickr.com/65535/51669868948_8126a7f232_o.gif",
    "link_bin": "https://github.com/lmbstudiocontact/mb6_1/raw/main/2241.bin",
    "id_bin": "2241",
    "list_language": [],
    "array_tags": [
      "digital",
      "distance",
      "weekday",
      "digi",
      "calories",
      "battery",
      "steps",
      "analog",
      "weather",
      "pulse",
      "pai",
      "time",
      "status"
    ],
    "list_album": [
      {
        "id_album": "2433880",
        "link_thumb": "https://live.staticflickr.com/65535/51669868948_8126a7f232_o.gif",
        "title": "None"
      }
    ]
  },
  {
    "author": "ZanarkTempest",
    "link_thumb": "https://live.staticflickr.com/65535/51670295249_fdecedc185_o.gif",
    "link_bin": "https://github.com/lmbstudiocontact/mb6_1/raw/main/2102.bin",
    "id_bin": "2102",
    "list_language": [],
    "array_tags": [
      "movies",
      "analog",
      "geek",
      "serie",
      "animated",
      "lcar",
      "animation"
    ],
    "list_album": [
      {
        "id_album": "2433880",
        "link_thumb": "https://live.staticflickr.com/65535/51670295249_fdecedc185_o.gif",
        "title": "None"
      }
    ]
  },
  {
    "author": "Raynk",
    "link_thumb": "https://live.staticflickr.com/65535/51669764076_d4aa26dab8_o.gif",
    "link_bin": "https://github.com/lmbstudiocontact/mb6_0/raw/main/704.bin",
    "id_bin": "704",
    "list_language": [],
    "array_tags": [
      "orange",
      "date",
      "zenitsu",
      "battery",
      "agatsuma",
      "steps",
      "anime"
    ],
    "list_album": [
      {
        "id_album": "63410260",
        "link_thumb": "https://live.staticflickr.com/65535/51669764076_d4aa26dab8_o.gif",
        "title": "Anime"
      }
    ]
  },
  {
    "author": "magnim",
    "link_thumb": "https://live.staticflickr.com/65535/51668948567_f0a37030e6_o.gif",
    "link_bin": "https://github.com/lmbstudiocontact/mb6_0/raw/main/618.bin",
    "id_bin": "618",
    "list_language": [],
    "array_tags": [
      "digital",
      "amoled",
      "weather",
      "pulse",
      "calories",
      "steps",
      "colors"
    ],
    "list_album": [
      {
        "id_album": "2433880",
        "link_thumb": "https://live.staticflickr.com/65535/51668948567_f0a37030e6_o.gif",
        "title": "None"
      }
    ]
  },
  {
    "author": "kvdkvd",
    "link_thumb": "https://live.staticflickr.com/65535/51668692027_dba47679ff_o.gif",
    "link_bin": "https://github.com/lmbstudiocontact/mb6_0/raw/main/1280.bin",
    "id_bin": "1280",
    "list_language": [],
    "array_tags": [
      "digital",
      "date",
      "distance",
      "heartrate",
      "weather",
      "battery",
      "steps"
    ],
    "list_album": [
      {
        "id_album": "2433880",
        "link_thumb": "https://live.staticflickr.com/65535/51668692027_dba47679ff_o.gif",
        "title": "None"
      }
    ]
  },
  {
    "author": "gfzt",
    "link_thumb": "https://live.staticflickr.com/65535/51670579900_1132fa0e3b_o.gif",
    "link_bin": "https://github.com/lmbstudiocontact/mb6_0/raw/main/4.bin",
    "id_bin": "4",
    "list_language": [],
    "array_tags": [
      "date",
      "heartrate",
      "steps"
    ],
    "list_album": [
      {
        "id_album": "-2075887794",
        "link_thumb": "https://live.staticflickr.com/65535/51670579900_1132fa0e3b_o.gif",
        "title": "Cartoon"
      }
    ]
  },
  {
    "author": "zyfish",
    "link_thumb": "https://live.staticflickr.com/65535/51668924632_14a04ffc9d_o.gif",
    "link_bin": "https://github.com/lmbstudiocontact/mb6_0/raw/main/5.bin",
    "id_bin": "5",
    "list_language": [],
    "array_tags": [
      "digital",
      "date",
      "heartrate",
      "weather",
      "battery",
      "steps"
    ],
    "list_album": [
      {
        "id_album": "2433880",
        "link_thumb": "https://live.staticflickr.com/65535/51668924632_14a04ffc9d_o.gif",
        "title": "None"
      }
    ]
  },
  {
    "author": "TsReal30",
    "link_thumb": "https://live.staticflickr.com/65535/51668674287_62d0d2abc3_o.gif",
    "link_bin": "https://github.com/lmbstudiocontact/mb6_0/raw/main/1110.bin",
    "id_bin": "1110",
    "list_language": [],
    "array_tags": [
      "face",
      "band",
      "pacman"
    ],
    "list_album": [
      {
        "id_album": "2211858",
        "link_thumb": "https://live.staticflickr.com/65535/51668674287_62d0d2abc3_o.gif",
        "title": "Game"
      }
    ]
  },
  {
    "author": "sebastianvila",
    "link_thumb": "https://live.staticflickr.com/65535/51670403129_eb63208916_o.gif",
    "link_bin": "https://github.com/lmbstudiocontact/mb6_0/raw/main/474.bin",
    "id_bin": "474",
    "list_language": [],
    "array_tags": [
      "boca",
      "simple"
    ],
    "list_album": [
      {
        "id_album": "2433880",
        "link_thumb": "https://live.staticflickr.com/65535/51670403129_eb63208916_o.gif",
        "title": "None"
      }
    ]
  }
]